LICENCE.md
MANIFEST.in
README.rst
setup.py
errordite/__init__.py
errordite/handlers.py
errordite/tests.py
errordite.egg-info/PKG-INFO
errordite.egg-info/SOURCES.txt
errordite.egg-info/dependency_links.txt
errordite.egg-info/requires.txt
errordite.egg-info/top_level.txt