Metadata-Version: 1.1
Name: errordite
Version: 0.2.2
Summary: Errordite exception logging.
Home-page: https://github.com/hugorodgerbrown/python-errordite
Author: Hugo Rodger-Brown
Author-email: hugo@rodger-brown.com
License: Copyright (c) 2013, Hugo Rodger-Brown
